pyiceberg_jdbc/catalog.py
pyiceberg_jdbc/models.py
pyiceberg_jdbc-0.1.0.dist-info/LICENSE
pyiceberg_jdbc-0.1.0.dist-info/METADATA
pyiceberg_jdbc-0.1.0.dist-info/WHEEL
pyiceberg_jdbc-0.1.0.dist-info/RECORD
