Metadata-Version: 2.1
Name: pyiceberg-jdbc
Version: 0.1.0
Summary: 
License: MIT
Author: Hao Guan
Author-email: gh@raptium.net
Requires-Python: >=3.8,<4.0
Classifier: Development Status :: 2 - Pre-Alpha
Classifier: License :: OSI Approved :: MIT License
Classifier: Programming Language :: Python :: 3
Classifier: Programming Language :: Python :: 3.8
Classifier: Programming Language :: Python :: 3.9
Classifier: Programming Language :: Python :: 3.10
Classifier: Programming Language :: Python :: 3.11
Classifier: Topic :: Software Development :: Libraries :: Python Modules
Requires-Dist: SQLAlchemy (>=2.0.5,<3.0.0)
Requires-Dist: pyarrow (>=11.0.0,<12.0.0)
Requires-Dist: pyiceberg (>=0.3.0,<0.4.0)
